strategy_api/__init__.py
strategy_api/event/__init__.py
strategy_api/event/engine.py
strategy_api/strategies/__init__.py
strategy_api/strategies/strategy_demo.py
strategy_api/strategies/strategy_ma.py
strategy_api/strategies/template.py
strategy_api/test/__init__.py
strategy_api/test/test.py
strategy_api/tm_api/__init__.py
strategy_api/tm_api/base.py
strategy_api/tm_api/object.py
strategy_api/tm_api/tools.py
strategy_api/tm_api/Binance/__init__.py
strategy_api/tm_api/Binance/futureInverse.py
strategy_api/tm_api/Binance/futureUsdt.py
strategy_api/tm_api/Binance/spotGateway.py
strategy_api/tm_api/Okex/__init__.py
strategy_api/tm_api/Okex/gateway.py
strategy_api/tm_api/api/__init__.py
strategy_api/tm_api/api/rest/__init__.py
strategy_api/tm_api/api/rest/rest_client.py
strategy_api/tm_api/api/websocket/__init__.py
strategy_api/tm_api/api/websocket/websocket_client.py
strategy_api-1.3.0.2.dist-info/LICENSE
strategy_api-1.3.0.2.dist-info/METADATA
strategy_api-1.3.0.2.dist-info/WHEEL
strategy_api-1.3.0.2.dist-info/top_level.txt
strategy_api-1.3.0.2.dist-info/RECORD
