Metadata-Version: 2.1
Name: strategy-api
Version: 1.3.0.2
Summary: 仓位查询 API 添加
Home-page: https://gitee.com/Jason520deng/strategy_api
Author: Kevin
Author-email: 1782552261@qq.com
Classifier: Programming Language :: Python :: 3
Classifier: License :: OSI Approved :: MIT License
Classifier: Operating System :: OS Independent
License-File: LICENSE
